pysser/__init__.py
pysser/pysser.py
pysser/ssermainlinux.py
pysser/ssermainwin.py
pysser/runlib/__init__.py
pysser/runlib/pyarmor_runtime.pyd
pysser/runlib/pyarmor_runtime.so
pysser-1.1.26.dist-info/LICENSE
pysser-1.1.26.dist-info/METADATA
pysser-1.1.26.dist-info/WHEEL
pysser-1.1.26.dist-info/top_level.txt
pysser-1.1.26.dist-info/RECORD
